glue_samp/__init__.py
glue_samp/menubar.py
glue_samp/samp_client.py
glue_samp/samp_state.py
glue_samp/version.py
glue_samp/qt/__init__.py
glue_samp/qt/layer_actions.py
glue_samp/qt/samp_client.py
glue_samp/tests/__init__.py
glue_samp/tests/test_samp_client.py
glue_samp-0.2.dist-info/LICENSE
glue_samp-0.2.dist-info/METADATA
glue_samp-0.2.dist-info/WHEEL
glue_samp-0.2.dist-info/entry_points.txt
glue_samp-0.2.dist-info/top_level.txt
glue_samp-0.2.dist-info/zip-safe
glue_samp-0.2.dist-info/RECORD
