Metadata-Version: 2.1
Name: glue-samp
Version: 0.2
Summary: A SAMP plugin for glue
Home-page: https://github.com/glue-viz/glue-samp
Author: Thomas Robitaille
Author-email: thomas.robitaille@gmail.com
License: UNKNOWN
Platform: UNKNOWN
Requires-Dist: astropy
Requires-Dist: glue-core (>=0.15)
Requires-Dist: numpy
Requires-Dist: qtpy
Provides-Extra: test
Requires-Dist: pytest ; extra == 'test'
Requires-Dist: pytest-cov ; extra == 'test'
Requires-Dist: pytest-faulthandler ; extra == 'test'
Requires-Dist: mock ; extra == 'test'
